stringhandling
