Metadata-Version: 2.1
Name: stringhandling
Version: 0.3
Summary: Python package for string handling
Author: Subeesh Palamadathil
Author-email: subi4020@gmail.com
License: MIT
License-File: LICENSE.md
